threed_strudel/__init__.py
threed_strudel/configure.py
threed_strudel/nomenclature.py
threed_strudel/average/__init__.py
threed_strudel/average/map_averaging.py
threed_strudel/average/superimpose_chimerax.py
threed_strudel/average/inp/global_reference.pdb
threed_strudel/bin/__init__.py
threed_strudel/bin/strudel_chopModelMapMPI.py
threed_strudel/bin/strudel_mapAveraging.py
threed_strudel/bin/strudel_mapMotifValidation.py
threed_strudel/bin/strudel_penultimateClassifier.py
threed_strudel/bin/strudel_runValidationBatch.py
threed_strudel/bin/strudel_sequenceFinder.py
threed_strudel/bin/strudel_setChimeraX.py
threed_strudel/bin/strudel_ultimateClassifier.py
threed_strudel/chop/__init__.py
threed_strudel/chop/chop_map.py
threed_strudel/chop/chop_map_old.py
threed_strudel/chop/chop_model_map_mpi.py
threed_strudel/chop/segment_residue_map.py
threed_strudel/classify/__init__.py
threed_strudel/classify/align_principal_axes.py
threed_strudel/classify/penultimate_classifier.py
threed_strudel/classify/rotamer_classifier.py
threed_strudel/classify/rotamer_utils.py
threed_strudel/classify/ultimate_classifier.py
threed_strudel/classify/inp/__init__.py
threed_strudel/lib/__init__.py
threed_strudel/lib/molprobity/rota8000-arg.data
threed_strudel/lib/molprobity/rota8000-asn.data
threed_strudel/lib/molprobity/rota8000-asp.data
threed_strudel/lib/molprobity/rota8000-cys.data
threed_strudel/lib/molprobity/rota8000-gln.data
threed_strudel/lib/molprobity/rota8000-glu.data
threed_strudel/lib/molprobity/rota8000-his.data
threed_strudel/lib/molprobity/rota8000-ile.data
threed_strudel/lib/molprobity/rota8000-leu.data
threed_strudel/lib/molprobity/rota8000-lys.data
threed_strudel/lib/molprobity/rota8000-met.data
threed_strudel/lib/molprobity/rota8000-phe.data
threed_strudel/lib/molprobity/rota8000-pro.data
threed_strudel/lib/molprobity/rota8000-ser.data
threed_strudel/lib/molprobity/rota8000-thr.data
threed_strudel/lib/molprobity/rota8000-trp.data
threed_strudel-0.9.18.dist-info/LICENSE.txt
threed_strudel-0.9.18.dist-info/METADATA
threed_strudel-0.9.18.dist-info/WHEEL
threed_strudel-0.9.18.dist-info/top_level.txt
threed_strudel-0.9.18.dist-info/RECORD
