Metadata-Version: 2.1
Name: threed-strudel
Version: 0.9.18
Summary: Strudel package
Home-page: UNKNOWN
Author: Andrei Istrate
Author-email: andrei@ebi.ac.uk
License: Apache License
Platform: UNKNOWN
Requires-Python: >=2.6
Requires-Dist: scipy
Requires-Dist: biopython
Requires-Dist: numpy
Requires-Dist: mrcfile
Requires-Dist: psutil
